{
    "node_name": [
        "evmos-node",
        "haqq-node",
        "lava-node",
        "lava-cache",
        "lava-provider",
        "massa-node",
        "near-node"
    ],
    "include": [
        {
            "git_url": "https://github.com",
            "git_api_url": "https://api.github.com/repos"
        },
        {
            "node_name": "evmos-node",
            "project_name": "evmos",
            "git_repository": "evmos/evmos",
            "node_type": "node",
            "binary": "evmosd"
        },
        {
            "node_name": "haqq-node",
            "project_name": "haqq",
            "git_repository": "haqq-network/haqq",
            "node_type": "node",
            "binary": "haqqd"
        },
        {
            "node_name": "lava-node",
            "project_name": "lava",
            "git_repository": "lavanet/lava",
            "node_type": "node",
            "binary": "lavad"
        },
        {
            "node_name": "lava-cache",
            "project_name": "lava",
            "git_repository": "lavanet/lava",
            "node_type": "cache",
            "binary": "lavap"
        },
        {
            "node_name": "lava-provider",
            "project_name": "lava",
            "git_repository": "lavanet/lava",
            "node_type": "provider",
            "binary": "lavap"
        },
        {
            "node_name": "massa-node",
            "project_name": "massa",
            "git_repository": "massalabs/massa",
            "node_type": "node",
            "binary": "massa-node"
        },
        {
            "node_name": "near-node",
            "project_name": "near",
            "git_repository": "near/nearcore",
            "node_type": "node",
            "binary": "neard"
        }
    ]
}